datadog_export/__init__.py
datadog_export/__main__.py
datadog_export/cli.py
datadog_export/config.py
datadog_export/events.py
datadog_export/exporter.py
datadog_export/logger.py
datadog_export/metrics.py
datadog_export/names.py
datadog_export/click_argument_types/__init__.py
datadog_export/click_argument_types/click_datetime.py
datadog_export/click_argument_types/click_duration.py
datadog_export/click_argument_types/click_regex.py
datadog_exporter-0.8.0.dist-info/LICENSE
datadog_exporter-0.8.0.dist-info/METADATA
datadog_exporter-0.8.0.dist-info/WHEEL
datadog_exporter-0.8.0.dist-info/entry_points.txt
datadog_exporter-0.8.0.dist-info/top_level.txt
datadog_exporter-0.8.0.dist-info/RECORD
