Metadata-Version: 2.1
Name: datadog-exporter
Version: 0.8.0
Summary: CLI for exporting datadog metrics
Home-page: https://github.com/binxio/datadog-exporter
Author: Mark van Holsteijn
Author-email: mark@binx.io
License: Apache2
Platform: any
Classifier: Development Status :: 3 - Alpha
Classifier: Environment :: Console
Classifier: Intended Audience :: Developers
Classifier: License :: OSI Approved :: BSD License
Classifier: Operating System :: POSIX
Classifier: Operating System :: MacOS
Classifier: Operating System :: Unix
Classifier: Operating System :: Microsoft :: Windows
Classifier: Programming Language :: Python
Classifier: Programming Language :: Python :: 3
Classifier: Topic :: Software Development :: Libraries :: Python Modules
License-File: LICENSE
Requires-Dist: boto3
Requires-Dist: click
Requires-Dist: pytz
Requires-Dist: durations
Requires-Dist: tzlocal
Requires-Dist: datadog
Requires-Dist: requests
Requires-Dist: python-dateutil
